totob12/__init__.py
totob12/math.py
totob12/weather.py
totob12-0.2.3.dist-info/METADATA
totob12-0.2.3.dist-info/WHEEL
totob12-0.2.3.dist-info/top_level.txt
totob12-0.2.3.dist-info/RECORD
